pyvisa_proxy/__init__.py
pyvisa_proxy/__main__.py
pyvisa_proxy/_main.py
pyvisa_proxy/_version_handling.py
pyvisa_proxy/highlevel.py
pyvisa_proxy/proxy_resource.py
pyvisa_proxy/proxy_server.py
pyvisa_proxy/rpc_client.py
pyvisa_proxy/data/job.schema.json
PyVISA_proxy-0.1.3.dist-info/AUTHORS
PyVISA_proxy-0.1.3.dist-info/LICENSE
PyVISA_proxy-0.1.3.dist-info/METADATA
PyVISA_proxy-0.1.3.dist-info/WHEEL
PyVISA_proxy-0.1.3.dist-info/top_level.txt
PyVISA_proxy-0.1.3.dist-info/RECORD
