Metadata-Version: 2.1
Name: PyVISA-proxy
Version: 0.1.3
Summary: PyVISA remote proxy server and client in order to address "remote" hardware as local
Home-page: https://github.com/casabre/pyvisa-proxy
Author: Carsten Sauerbrey
Author-email: carsten.sauerbrey@gmail.com
Maintainer: Carsten Sauerbrey
Maintainer-email: carsten.sauerbrey@gmail.com
License: MIT
Keywords: Remote,VISA,GPIB,USB,serial,RS232,measurement,acquisition,zmq
Platform: Linux; Windows; Mac
Classifier: Development Status :: 4 - Beta
Classifier: Intended Audience :: Developers
Classifier: Intended Audience :: Science/Research
Classifier: License :: OSI Approved :: MIT License
Classifier: Operating System :: Microsoft :: Windows
Classifier: Operating System :: POSIX :: Linux
Classifier: Operating System :: MacOS :: MacOS X
Classifier: Programming Language :: Python
Classifier: Topic :: Scientific/Engineering :: Interface Engine/Protocol Translator
Classifier: Topic :: Software Development :: Libraries :: Python Modules
Classifier: Programming Language :: Python :: 3.8
Classifier: Programming Language :: Python :: 3.9
Classifier: Programming Language :: Python :: 3.10
Classifier: Programming Language :: Python :: 3.11
Classifier: Programming Language :: Python :: 3.12
Requires-Python: >=3.8
License-File: LICENSE
License-File: AUTHORS
Requires-Dist: pyvisa >=1.12.0
Requires-Dist: pyvisa-py
Requires-Dist: pyzmq
Requires-Dist: jsonschema
Requires-Dist: tblib
Requires-Dist: dill
Requires-Dist: six
Requires-Dist: packaging
Provides-Extra: docs
Requires-Dist: sphinx ; extra == 'docs'
Requires-Dist: sphinx-rtd-theme ; extra == 'docs'
Requires-Dist: myst-parser ; extra == 'docs'
Provides-Extra: test
Requires-Dist: pytest ; extra == 'test'
Requires-Dist: coverage[toml] ; extra == 'test'
Requires-Dist: pytest-cov ; extra == 'test'
Requires-Dist: pytest-asyncio ; extra == 'test'
Requires-Dist: pyvisa-sim ; extra == 'test'
